{"numlevels":"4","numquestions":"3","title":"Subtraction Warmup","description":"It is important that you be able to do subtraction questions in your head.  This take practice.  Warm up with these questions","sesskey":"LDr3BRsWWa","_qf__local_gamecreator_game_form_balloons_form2":"1","mform_isexpanded_id_levelheader0":"1","mform_isexpanded_id_levelheader1":"1","mform_isexpanded_id_levelheader2":"1","mform_isexpanded_id_levelheader3":"1","mform_isexpanded_id_levelheader4":"1","levelname0":"Level 1","levelspeed0":"0","q_00":"35 - 23","a_00":"12","o_000":"22","o_001":"28","o_002":"15","o_003":"18","q_01":"78 - 32","a_01":"46","o_010":"36","o_011":"56","o_012":"45","o_013":"47","q_02":"96 - 76","a_02":"20","o_020":"30","o_021":"10","o_022":"19","o_023":"22","q_03":"68 - 56","a_03":"12","o_030":"22","o_031":"13","o_032":"11","o_033":"21","levelname1":"Level 2","levelspeed1":"0","q_10":"78 - 36","a_10":"42","o_100":"44","o_101":"43","o_102":"32","o_103":"52","q_11":"74 - 52","a_11":"22","o_110":"23","o_111":"21","o_112":"12","o_113":"32","q_12":"69 - 31","a_12":"38","o_120":"48","o_121":"28","o_122":"37","o_123":"39","q_13":"65 - 12","a_13":"53","o_130":"43","o_131":"52","o_132":"54","o_133":"34","levelname2":"Level 3","levelspeed2":"0","q_20":"77 - 46","a_20":"31","o_200":"21","o_201":"41","o_202":"32","o_203":"30","q_21":"88 - 74","a_21":"14","o_210":"24","o_211":"23","o_212":"13","o_213":"15","q_22":"89 - 35","a_22":"54","o_220":"53","o_221":"55","o_222":"44","o_223":"64","q_23":"55 - 13","a_23":"42","o_230":"41","o_231":"43","o_232":"32","o_233":"52","levelname3":"Level 4","levelspeed3":"0","q_30":"79 - 13","a_30":"66","o_300":"56","o_301":"46","o_302":"57","o_303":"55","q_31":"84 - 23","a_31":"61","o_310":"60","o_311":"62","o_312":"51","o_313":"71","q_32":"67 - 31","a_32":"36","o_320":"46","o_321":"26","o_322":"25","o_323":"37","q_33":"99 - 29","a_33":"70","o_330":"80","o_331":"71","o_332":"60","o_333":"69","levelname4":"Level 5","levelspeed4":"0","q_40":"58 - 24","a_40":"34","o_400":"33","o_401":"35","o_402":"44","o_403":"24","q_41":"95 - 31","a_41":"64","o_410":"54","o_411":"74","o_412":"63","o_413":"66","q_42":"56 - 31","a_42":"25","o_420":"35","o_421":"15","o_422":"26","o_423":"24","q_43":"66 - 56","a_43":"10","o_430":"9","o_431":"20","o_432":"11","o_433":"13","submitbutton":"Create Game"}